medwave_extended_sql/__init__.py
medwave_extended_sql/async_manager.py
medwave_extended_sql/models.py
medwave_extended_sql/utils.py
medwave_extended_sql-0.2.3.dist-info/METADATA
medwave_extended_sql-0.2.3.dist-info/WHEEL
medwave_extended_sql-0.2.3.dist-info/RECORD
